ndcpyr/__init__.py
ndcpyr/preprocessing/__init__.py
ndcpyr/preprocessing/api.py
ndcpyr/preprocessing/core.py
ndcpyr-0.1.0.dist-info/LICENSE
ndcpyr-0.1.0.dist-info/METADATA
ndcpyr-0.1.0.dist-info/WHEEL
ndcpyr-0.1.0.dist-info/top_level.txt
ndcpyr-0.1.0.dist-info/RECORD
